pyxray/__init__.py
pyxray/exceptions.py
pyxray/test_xray.py
pyxray/xray.py
python_xray-0.3.1.dist-info/LICENSE
python_xray-0.3.1.dist-info/METADATA
python_xray-0.3.1.dist-info/WHEEL
python_xray-0.3.1.dist-info/top_level.txt
python_xray-0.3.1.dist-info/RECORD
